pyllrp/AutoDetect.py
pyllrp/LLRPConnector.py
pyllrp/ParseDef.py
pyllrp/TagInventory.py
pyllrp/TagWriter.py
pyllrp/TinyExample.py
pyllrp/__init__.py
pyllrp/llrpdef.py
pyllrp/pyllrp.py
pyllrp/pypi.py
pyllrp-3.1.1.dist-info/METADATA
pyllrp-3.1.1.dist-info/WHEEL
pyllrp-3.1.1.dist-info/top_level.txt
pyllrp-3.1.1.dist-info/RECORD
