Metadata-Version: 2.1
Name: pyllrp
Version: 3.1.1
Summary: A complete implementation of LLRP (Low Level Reader Protocol) in pure Python.
Home-page: http://www.sites.google.com/site/crossmgrsoftware/
Author: Edward Sitarski
Author-email: Edward Sitarski <edward.sitarski@gmail.com>
License: 
Project-URL: Homepage, https://github.com/esitarski/pyllrp
Project-URL: Repository, https://github.com/esitarski/pyllrp
Project-URL: Issues, https://github.com/esitarski/pyllrp/issues
Keywords: LLRP,RFID,Impinj Reader
Classifier: Development Status :: 5 - Production/Stable
Classifier: Intended Audience :: Developers
Classifier: Topic :: System :: Hardware :: Hardware Drivers
Classifier: License :: OSI Approved :: MIT License
Classifier: Programming Language :: Python :: 3.8
Classifier: Programming Language :: Python :: 3.9
Classifier: Programming Language :: Python :: 3.10
Classifier: Programming Language :: Python :: 3.11
Classifier: Programming Language :: Python :: 3.12
Requires-Python: >=3.8
Requires-Dist: bitstring>=3.1.1
